{
  "type": "FeatureCollection",
  "features": [
    {
      "type": "Feature",
      "properties": {
        "Name": "Polygon 2",
        "Description": ""
      },
      "geometry": {
        "type": "Polygon",
        "coordinates": [
          [
            [
              77.5835824,
              12.89203,
              0
            ],
            [
              77.5818229,
              12.892281,
              0
            ],
            [
              77.58178,
              12.8919672,
              0
            ],
            [
              77.58178,
              12.8911096,
              0
            ],
            [
              77.5819945,
              12.8909005,
              0
            ],
            [
              77.5827885,
              12.8903357,
              0
            ],
            [
              77.5842047,
              12.8899383,
              0
            ],
            [
              77.5856638,
              12.8894572,
              0
            ],
            [
              77.5916505,
              12.8884113,
              0
            ],
            [
              77.5916076,
              12.8897709,
              0
            ],
            [
              77.5883675,
              12.891026,
              0
            ],
            [
              77.5881529,
              12.8910678,
              0
            ],
            [
              77.5877881,
              12.8912142,
              0
            ],
            [
              77.5871658,
              12.8910469,
              0
            ],
            [
              77.5861144,
              12.8916325,
              0
            ],
            [
              77.5849986,
              12.8919254,
              0
            ],
            [
              77.5835824,
              12.89203,
              0
            ]
          ]
        ]
      }
    },
    {
      "type": "Feature",
      "properties": {
        "marker-color": "#0000ff",
        "marker-size": "medium",
        "marker-symbol": "star",
        "locality": "JP Nagar",
        "ambassador": "Chandana",
        "ambassador_email": "chandana@gmail.com",
        "ambassador_photo_profile": "http://chandana.com"
      },
      "geometry": {
        "type": "Point",
        "coordinates": [
          77.58748769760132,
          12.891193293444498
        ]
      }
    },
    {
      "type": "Feature",
      "properties": {
        "marker-color": "#008000",
        "marker-size": "medium",
        "marker-symbol": "circle"
      },
      "geometry": {
        "type": "Point",
        "coordinates": [
          77.59162902832031,
          12.889143434519998
        ]
      }
    },
    {
      "type": "Feature",
      "properties": {
        "marker-color": "#008000",
        "marker-size": "medium",
        "marker-symbol": "circle"
      },
      "geometry": {
        "type": "Point",
        "coordinates": [
          77.58572816848755,
          12.88943627253674
        ]
      }
    },
    {
      "type": "Feature",
      "properties": {
        "marker-color": "#008000",
        "marker-size": "medium",
        "marker-symbol": "circle"
      },
      "geometry": {
        "type": "Point",
        "coordinates": [
          77.5818657875061,
          12.89215546633524
        ]
      }
    }
  ]
}